<?xml version="1.0" encoding="utf-8" standalone="yes"?>
<PACKAGE>
  <DELETE>
    <offers />
    <pictures />
  </DELETE>
  <offer>
    <signature>290/6093/ODS</signature>
    <parameters>
      <p id="1">290/6093/ODS</p>
      <p id="2">Biuro Nieruchomości DAN-DOM</p>
      <p id="3">2026-03-25 11:23:06.0038</p>
      <p id="5">2026-01-20 12:37:29.0391</p>
      <p id="10">920000.0000</p>
      <p id="13">7931.0300</p>
      <p id="20">WOLNO STOJĄCY</p>
      <p id="23">OTWARTA</p>
      <p id="26">AKTUALNA</p>
      <p id="36">DOM</p>
      <p id="39">KAN. MIEJSKA</p>
      <p id="43">SPRZEDAŻ</p>
      <p id="45">WIELKOPOLSKIE</p>
      <p id="46">OBORNICKI</p>
      <p id="47">ROGOŹNO</p>
      <p id="48">GARBATKA</p>
      <p id="49"></p>
      <p id="51">0.0000</p>
      <p id="52"></p>
      <p id="53"></p>
      <p id="54">PŁASKIE</p>
      <p id="59"></p>
      <p id="60">POLSKA</p>
      <p id="61">1202.0000</p>
      <p id="63">0.0000</p>
      <p id="71">2023</p>
      <p id="72">WYSOKI STANDARD</p>
      <p id="77">DACHÓWKA CERAMICZNA</p>
      <p id="78">PCV, Z ROLETAMI</p>
      <p id="79">4.0000</p>
      <p id="81">CZĘŚCIOWO</p>
      <p id="83">2.0000</p>
      <p id="84">1.0000</p>
      <p id="87">PIEC GAZOWY</p>
      <p id="89">C.O. GAZOWE,C.O. WŁASNE</p>
      <p id="93">215280.0000</p>
      <p id="94">249688.0000</p>
      <p id="121">WŁASNOŚĆ</p>
      <p id="128">116.0000</p>
      <p id="141">PLN</p>
      <p id="154"></p>
      <p id="157">ELEKTRYCZNA, WODNA, GAZOWA</p>
      <p id="161">GARAŻ</p>
      <p id="170">501-769-166</p>
      <p id="171">dan-dom@wp.pl</p>
      <p id="172">577</p>
      <p id="174">34716.0000</p>
      <p id="201"></p>
      <p id="202"></p>
      <p id="220">WTÓRNY</p>
      <p id="305">Danuta Majchrzak</p>
      <p id="307">NIE</p>
      <p id="340"></p>
      <p id="341"></p>
      <p id="342"></p>
      <p id="343"></p>
      <p id="344"></p>
      <p id="345"></p>
      <p id="489">TAK</p>
      <p id="491">Nowoczesny dom jednorodzinny z garażem</p>
      <p id="492">NIE</p>
    </parameters>
    <pictures>
      <picture>
        <unique>110351698.jpg</unique>
        <status>1</status>
        <weight>1</weight>
        <description />
      </picture>
      <picture>
        <unique>110351692.jpg</unique>
        <status>0</status>
        <weight>2</weight>
        <description />
      </picture>
      <picture>
        <unique>110351694.jpg</unique>
        <status>0</status>
        <weight>3</weight>
        <description />
      </picture>
      <picture>
        <unique>110351715.jpg</unique>
        <status>0</status>
        <weight>4</weight>
        <description />
      </picture>
      <picture>
        <unique>110351721.jpg</unique>
        <status>0</status>
        <weight>5</weight>
        <description />
      </picture>
      <picture>
        <unique>110351725.jpg</unique>
        <status>0</status>
        <weight>6</weight>
        <description />
      </picture>
      <picture>
        <unique>110351711.jpg</unique>
        <status>0</status>
        <weight>7</weight>
        <description />
      </picture>
      <picture>
        <unique>110351727.jpg</unique>
        <status>0</status>
        <weight>8</weight>
        <description />
      </picture>
      <picture>
        <unique>110351733.jpg</unique>
        <status>0</status>
        <weight>9</weight>
        <description />
      </picture>
      <picture>
        <unique>110351730.jpg</unique>
        <status>0</status>
        <weight>10</weight>
        <description />
      </picture>
      <picture>
        <unique>110351703.jpg</unique>
        <status>0</status>
        <weight>11</weight>
        <description />
      </picture>
      <picture>
        <unique>110351729.jpg</unique>
        <status>0</status>
        <weight>12</weight>
        <description />
      </picture>
      <picture>
        <unique>110352118.jpg</unique>
        <status>0</status>
        <weight>13</weight>
        <description />
      </picture>
      <picture>
        <unique>110351736.jpg</unique>
        <status>0</status>
        <weight>14</weight>
        <description />
      </picture>
      <picture>
        <unique>110812640.jpg</unique>
        <status>0</status>
        <weight>15</weight>
        <description />
      </picture>
      <picture>
        <unique>110812641.jpg</unique>
        <status>0</status>
        <weight>16</weight>
        <description />
      </picture>
      <picture>
        <unique>110812643.jpg</unique>
        <status>0</status>
        <weight>17</weight>
        <description />
      </picture>
    </pictures>
    <description>Polecamy na sprzedaż piękną nieruchomość, położoną w Garbatce, gm. Rogoźno.&lt;br/&gt;&lt;br/&gt;Współpraca z nami - kupując tę nieruchomość, zyskujesz kompleksową opiekę prawną oraz pomoc w uzyskaniu finansowania.&lt;br/&gt;Informujemy, że usługa pośrednictwa jest płatna zgodnie z regulaminem biura.&lt;br/&gt;&lt;br/&gt;Ofertę stanowi dom jednorodzinny, parterowy, z garażem jednostanowiskowym o powierzchni łącznej 116 m2. Usytuowany jest na działce o powierzchni 1.202m2.&lt;br/&gt;Układ pomieszczeń: wiatrołap, korytarz, otwarta kuchnia, salon, 3 sypialnie, łazienka, wc, pomieszczenie gospodarcze oraz garaż. Kuchnia w meblach w zabudowie bez sprzętów. Brama garażowa oraz wjazdowa sterowane pilotem. Nieruchomość ogrodzona.&lt;br/&gt;&lt;br/&gt;Okna pcv z roletami zewnętrznymi, ogrzewanie gazowe. Media: prąd, gaz, woda miejska, kanalizacja. W pomieszczeniu gospodarczym zamontowany zmiękczacz wody.&lt;br/&gt;&lt;br/&gt;Wnętrze urządzone w naturalnych, jasnych kolorach, pomieszczenia ustawne i komfortowe. Nieruchomość gotowa do zamieszkania!&lt;br/&gt;&lt;br/&gt;Serdecznie zachęcamy do oglądania!&lt;br/&gt;&lt;br/&gt;Osoba prowadząca ofertę:  Joanna Szewczak 506-54-11-11, Danuta Majchrzak 501-769-166.&lt;br/&gt;&lt;br/&gt;W razie dodatkowych pytań służymy pomocą, również przy uzyskaniu kredytu na zakup.&lt;br/&gt;&lt;br/&gt;Zachęcamy do korzystania z naszego profilu na Facebook:&lt;br/&gt;https://www.facebook.com/biurodandom

</description>
  </offer>
</PACKAGE>