<?xml version="1.0" encoding="utf-8" standalone="yes"?>
<PACKAGE>
  <DELETE>
    <offers>
      <signature>293/6093/ODS</signature>
    </offers>
    <pictures />
  </DELETE>
  <offer>
    <signature>103/6093/OMW</signature>
    <parameters>
      <p id="1">103/6093/OMW</p>
      <p id="2">Biuro Nieruchomości DAN-DOM</p>
      <p id="3">2026-04-10 11:56:31.0306</p>
      <p id="5">2026-02-20 15:23:33.0749</p>
      <p id="10">1300.0000</p>
      <p id="11">1300.0000</p>
      <p id="14">24.0741</p>
      <p id="19">2-POKOJOWE</p>
      <p id="23">ODDZIELNA</p>
      <p id="26">AKTUALNA</p>
      <p id="36">MIESZKANIE</p>
      <p id="38"></p>
      <p id="43">WYNAJEM</p>
      <p id="45">WIELKOPOLSKIE</p>
      <p id="46">WĄGROWIECKI</p>
      <p id="47">WĄGROWIEC</p>
      <p id="48">WĄGROWIEC</p>
      <p id="49"></p>
      <p id="51">0.0000</p>
      <p id="52"></p>
      <p id="59">DOMOFON</p>
      <p id="60">POLSKA</p>
      <p id="62">2.0000</p>
      <p id="63">4.0000</p>
      <p id="70">BLOK</p>
      <p id="72">DOBRY</p>
      <p id="78">PCV</p>
      <p id="79">2.0000</p>
      <p id="82"></p>
      <p id="83">1.0000</p>
      <p id="86"></p>
      <p id="89">C.O. Z SIECI MIEJSKIEJ</p>
      <p id="93">305.1100</p>
      <p id="94">356.0700</p>
      <p id="128">54.0000</p>
      <p id="131">305.1100</p>
      <p id="132">356.0700</p>
      <p id="141">PLN</p>
      <p id="170">501-769-166</p>
      <p id="171">dan-dom@wp.pl</p>
      <p id="172">577</p>
      <p id="174">34716.0000</p>
      <p id="201"></p>
      <p id="202"></p>
      <p id="220">WTÓRNY</p>
      <p id="300">Osiedle Niepodległości</p>
      <p id="305">Danuta Majchrzak</p>
      <p id="307">NIE</p>
      <p id="340"></p>
      <p id="341"></p>
      <p id="342"></p>
      <p id="343"></p>
      <p id="344"></p>
      <p id="345"></p>
      <p id="349">NIE</p>
      <p id="489">TAK</p>
      <p id="491">Mieszkanie w świetnej lokalizacji 2 pokoje</p>
      <p id="492">NIE</p>
    </parameters>
    <pictures>
      <picture>
        <unique>110869537.jpg</unique>
        <status>1</status>
        <weight>1</weight>
        <description />
      </picture>
      <picture>
        <unique>110869538.jpg</unique>
        <status>0</status>
        <weight>2</weight>
        <description />
      </picture>
      <picture>
        <unique>110869539.jpg</unique>
        <status>0</status>
        <weight>3</weight>
        <description />
      </picture>
      <picture>
        <unique>110869540.jpg</unique>
        <status>0</status>
        <weight>4</weight>
        <description />
      </picture>
      <picture>
        <unique>110869541.jpg</unique>
        <status>0</status>
        <weight>5</weight>
        <description />
      </picture>
      <picture>
        <unique>110869542.jpg</unique>
        <status>0</status>
        <weight>6</weight>
        <description />
      </picture>
      <picture>
        <unique>110869543.jpg</unique>
        <status>0</status>
        <weight>7</weight>
        <description />
      </picture>
      <picture>
        <unique>110869544.jpg</unique>
        <status>0</status>
        <weight>8</weight>
        <description />
      </picture>
      <picture>
        <unique>110869545.jpg</unique>
        <status>0</status>
        <weight>9</weight>
        <description />
      </picture>
    </pictures>
    <description>Do wynajęcia mieszkanie 2-pokojowe w świetnej lokalizacji miasta, wolne od zaraz!&lt;br/&gt;&lt;br/&gt;WYNAJEM NA WARUNKACH NAJMU OKAZJONALNEGO!&lt;br/&gt;Najemca zobowiązany jest wskazać inny lokal, w którym będzie mógł zamieszkać w przypadku egzekucji obowiązku opróżnienia lokalu. Musi on również dostarczyć do umowy najmu, oświadczenie właściciela innego lokalu - o wyrażeniu zgody na jego zamieszkanie.&lt;br/&gt;&lt;br/&gt;LOKALIZACJA:&lt;br/&gt;Miasto / dzielnica: Wągrowiec&lt;br/&gt;Ulica: Osiedle Niepodległości&lt;br/&gt;Okolica: ścisłe centrum osiedla, w sąsiedztwie bloki, sklepy, przychodnie, oraz wszystko co potrzebne do komfortowego życia&lt;br/&gt;&lt;br/&gt;SZCZEGÓŁY NIERUCHOMOŚCI&lt;br/&gt;Powierzchnia mieszkania: 54 m²&lt;br/&gt;Liczba pokoi: 2&lt;br/&gt;Piętro: 2&lt;br/&gt;Rodzaj budynku: blok&lt;br/&gt;Rok budowy: 1990&lt;br/&gt;Stan mieszkania: do zamieszkania&lt;br/&gt;Ogrzewanie: miejskie&lt;br/&gt;Ciepła woda: bojler elektryczny&lt;br/&gt;&lt;br/&gt;KOSZTY:&lt;br/&gt;Czynsz najmu: 1 300 zł/miesiąc&lt;br/&gt;Kaucja: 2 600 zł&lt;br/&gt;Opłata do Spółdzielni w wysokości ok. 650 zł/m-c, która zawiera m.in. zaliczki na ogrzewanie mieszkania, wodę, gaz. Pozostałe koszty związane z utrzymaniem to wyłącznie zużycie prądu.&lt;br/&gt;Prowizja biura: 1 000 zł - płatna jednorazowo w dniu podpisania umowy&lt;br/&gt;Notariusz: ok. 400 zł&lt;br/&gt;&lt;br/&gt;UKŁAD I WYPOSAŻENIE&lt;br/&gt;Duży pokój z balkonem&lt;br/&gt;Oddzielna kuchnia&lt;br/&gt;Sypialnia&lt;br/&gt;Łazienka z wanną&lt;br/&gt;Przedpokój&lt;br/&gt;Umeblowana kuchnia oraz wyposażona w sprzęt (lodówka, kuchenka gazowa, okap), w łazience pralka, w korytarzy zabudowy szafkowe.&lt;br/&gt;&lt;br/&gt;ATUTY NIERUCHOMOŚCI&lt;br/&gt;Świetna lokalizacja — wszędzie blisko, niemal każda instytucja "na wyciągnięcie ręki"&lt;br/&gt;Mieszkanie wolne do wprowadzenia&lt;br/&gt;&lt;br/&gt;DODATKOWE INFORMACJE&lt;br/&gt;Piwnica / komórka lokatorska: tak&lt;br/&gt;Balkon: tak&lt;br/&gt;Miejsce parkingowe: tak - na parkingach znajdujących się przy bloku&lt;br/&gt;Forma własności: spółdzielcze - własnościowe prawo&lt;br/&gt;&lt;br/&gt;KONTAKT&lt;br/&gt;Imię i nazwisko: Marta Janusz, licencja PFRN nr 28634&lt;br/&gt;Telefon: 519 110 078&lt;br/&gt;&lt;br/&gt;Serdecznie zachęcamy do oglądania!&lt;br/&gt;W razie dodatkowych pytań służymy pomocą, również przy uzyskaniu kredytu na zakup.&lt;br/&gt;&lt;br/&gt;Zachęcamy do korzystania z naszego profilu na Facebook:&lt;br/&gt;https://www.facebook.com/biurodandom

</description>
  </offer>
  <offer>
    <signature>107/6093/OMW</signature>
    <parameters>
      <p id="1">107/6093/OMW</p>
      <p id="2">Biuro Nieruchomości DAN-DOM</p>
      <p id="3">2026-04-10 11:53:20.0429</p>
      <p id="5">2026-03-10 16:35:15.0470</p>
      <p id="10">1200.0000</p>
      <p id="11">1200.0000</p>
      <p id="14">22.6415</p>
      <p id="19">2-POKOJOWE</p>
      <p id="23">ODDZIELNA</p>
      <p id="26">AKTUALNA</p>
      <p id="36">MIESZKANIE</p>
      <p id="38"></p>
      <p id="43">WYNAJEM</p>
      <p id="45">WIELKOPOLSKIE</p>
      <p id="46">OBORNICKI</p>
      <p id="47">ROGOŹNO</p>
      <p id="48">ROGOŹNO</p>
      <p id="49"></p>
      <p id="51">0.0000</p>
      <p id="52"></p>
      <p id="59">DOMOFON</p>
      <p id="60">POLSKA</p>
      <p id="62">3.0000</p>
      <p id="63">3.0000</p>
      <p id="70">BLOK</p>
      <p id="71">1992</p>
      <p id="72">DOBRY</p>
      <p id="78">PCV, Z ROLETAMI</p>
      <p id="79">2.0000</p>
      <p id="81">TAK</p>
      <p id="82">LOGGIA</p>
      <p id="83">1.0000</p>
      <p id="84">1.0000</p>
      <p id="86"></p>
      <p id="87">SIEĆ MIEJSKA</p>
      <p id="89">C.O. Z SIECI MIEJSKIEJ</p>
      <p id="93">281.6400</p>
      <p id="94">328.6800</p>
      <p id="128">53.0000</p>
      <p id="131">281.6400</p>
      <p id="132">328.6800</p>
      <p id="137">780.0000</p>
      <p id="141">PLN</p>
      <p id="170">501-769-166</p>
      <p id="171">dan-dom@wp.pl</p>
      <p id="172">577</p>
      <p id="174">34716.0000</p>
      <p id="201"></p>
      <p id="202"></p>
      <p id="220">WTÓRNY</p>
      <p id="300">Kościuszki</p>
      <p id="305">Danuta Majchrzak</p>
      <p id="307">NIE</p>
      <p id="340"></p>
      <p id="341"></p>
      <p id="342"></p>
      <p id="343"></p>
      <p id="344"></p>
      <p id="345"></p>
      <p id="349">NIE</p>
      <p id="489">TAK</p>
      <p id="491">Przytulny azyl w sercu miasta Rogoźno | 2 pokoje</p>
      <p id="492">NIE</p>
    </parameters>
    <pictures>
      <picture>
        <unique>111219237.jpg</unique>
        <status>1</status>
        <weight>1</weight>
        <description />
      </picture>
      <picture>
        <unique>111219240.jpg</unique>
        <status>0</status>
        <weight>2</weight>
        <description />
      </picture>
      <picture>
        <unique>111219229.jpg</unique>
        <status>0</status>
        <weight>3</weight>
        <description />
      </picture>
      <picture>
        <unique>111219231.jpg</unique>
        <status>0</status>
        <weight>4</weight>
        <description />
      </picture>
      <picture>
        <unique>111219239.jpg</unique>
        <status>0</status>
        <weight>5</weight>
        <description />
      </picture>
      <picture>
        <unique>111219236.jpg</unique>
        <status>0</status>
        <weight>6</weight>
        <description />
      </picture>
      <picture>
        <unique>111219232.jpg</unique>
        <status>0</status>
        <weight>7</weight>
        <description />
      </picture>
      <picture>
        <unique>111219234.jpg</unique>
        <status>0</status>
        <weight>8</weight>
        <description />
      </picture>
      <picture>
        <unique>111219235.jpg</unique>
        <status>0</status>
        <weight>9</weight>
        <description />
      </picture>
      <picture>
        <unique>111219233.jpg</unique>
        <status>0</status>
        <weight>10</weight>
        <description />
      </picture>
      <picture>
        <unique>111219238.jpg</unique>
        <status>0</status>
        <weight>11</weight>
        <description />
      </picture>
    </pictures>
    <description>Do wynajęcia przyjemne mieszkanie w centrum miasta w Rogoźnie - wolne do dyspozycji najemcy od zaraz! &lt;br/&gt;&lt;br/&gt;WYNAJEM NA WARUNKACH NAJMU OKAZJONALNEGO!&lt;br/&gt;Najemca zobowiązany jest wskazać inny lokal, w którym będzie mógł zamieszkać w przypadku obowiązku opuszczenia lokalu. Musi on również dostarczyć do umowy najmu, oświadczenie właściciela innego lokalu - o wyrażeniu zgody w przypadku konieczności na jego zamieszkanie.&lt;br/&gt;&lt;br/&gt;LOKALIZACJA:&lt;br/&gt;Miasto / dzielnica: Rogoźno, Centrum&lt;br/&gt;Ulica: Kościuszki&lt;br/&gt;Okolica: centrum miasta, lecz w odległości od ruchliwej głównej ulicy; osiedle bloków z miejscami parkingowymi do dyspozycji mieszkańców.&lt;br/&gt;W sąsiedztwie sklepy, markety, placówki bankowe, szkoły i przedszkola.&lt;br/&gt;&lt;br/&gt;SZCZEGÓŁY NIERUCHOMOŚCI&lt;br/&gt;Powierzchnia mieszkania: 53 m²&lt;br/&gt;Liczba pokoi: 2&lt;br/&gt;Piętro: 3&lt;br/&gt;Rodzaj budynku: blok&lt;br/&gt;Rok budowy: 1992&lt;br/&gt;Stan mieszkania: gotowe do zamieszkania - lokal estetyczny&lt;br/&gt;Ogrzewanie: miejskie&lt;br/&gt;Ciepła woda: miejska&lt;br/&gt;&lt;br/&gt;KOSZTY:&lt;br/&gt;Czynsz najmu: 1300 zł/miesiąc&lt;br/&gt;Kaucja zwrotna: 2500 zł&lt;br/&gt;Pozostałe koszty: czynsz do Spółdzielni tj. 780 zł dla dwóch osób - w tym niemal wszystkie opłaty za użytkowanie mieszkania, dodatkowo zużycie prądu, internet 65 zł/m-c, jeden raz w roku opłata za serwis uzdatniacza wody;&lt;br/&gt;Prowizja biura: 1 000 zł - płatna jednorazowo w dniu podpisania umowy, w usłudze biura pełna pomoc przy rygorze i oświadczeniu notarialnym&lt;br/&gt;Notariusz: ok. 350 zł&lt;br/&gt;&lt;br/&gt;Czas trwania najmu do uzgodnienia. Preferowany najemca małżeństwo lub para, także z dzieckiem. Akceptowane zwierzę domowe. &lt;br/&gt;&lt;br/&gt;UKŁAD I WYPOSAŻENIE&lt;br/&gt;Ładny salon z wyjściem na loggie&lt;br/&gt;Sypialnia&lt;br/&gt;Kuchnia&lt;br/&gt;Łazienka z wanną&lt;br/&gt;Oddzielna toaleta&lt;br/&gt;Korytarz&lt;br/&gt;&lt;br/&gt;Stan wyposażenia widoczny na zdjęciach. Kuchnia umeblowana oraz wyposażona w sprzęt (lodówka, zmywarka, piekarnik, płyta indukcyjna), w łazience także pralka.&lt;br/&gt;&lt;br/&gt;ATUTY NIERUCHOMOŚCI&lt;br/&gt;Świetna lokalizacja — wszędzie blisko, niemal każda instytucja "na wyciągnięcie ręki"&lt;br/&gt;Mieszkanie w dużej mierze umeblowane, wolne i gotowe do wprowadzenia&lt;br/&gt;&lt;br/&gt;DODATKOWE INFORMACJE&lt;br/&gt;Piwnica / komórka lokatorska: nie&lt;br/&gt;Balkon: tak, loggia&lt;br/&gt;Miejsce parkingowe: tak - na terenie przynależnym do bloku &lt;br/&gt;Forma własności: pełna własność&lt;br/&gt;&lt;br/&gt;KONTAKT&lt;br/&gt;Imię i nazwisko: Marta Janusz, licencja PFRN nr 28634&lt;br/&gt;Telefon: 519 110 078&lt;br/&gt;&lt;br/&gt;Serdecznie zachęcamy do oglądania!&lt;br/&gt;W razie dodatkowych pytań służymy pomocą, również przy uzyskaniu kredytu na zakup.&lt;br/&gt;&lt;br/&gt;Zachęcamy do korzystania z naszego profilu na Facebook:&lt;br/&gt;https://www.facebook.com/biurodandom

</description>
  </offer>
</PACKAGE>